{
  "baseline_version": "segment_sweep_v1",
  "candidate_version": "segment_sweep_v1",
  "scenarios": {
    "area_search_3uav": {
      "final_coverage_delta": 0.0,
      "time_to_95_delta_pct": 0.0,
      "total_distance_delta_pct": 0.0,
      "redundant_coverage_delta_pct": 0.0,
      "post_95_extra_distance_delta_pct": 0.0,
      "post_95_search_distance_delta_pct": 0.0,
      "workload_balance_delta": 0.0,
      "workload_balance_active_delta": 0.0,
      "segment_count_delta": 0.0,
      "unique_segment_count_delta": 0.0,
      "segment_workload_balance_delta": 0.0,
      "turn_rate_delta": 0.0,
      "no_fly_violations_delta": 0.0,
      "confirm_success_rate_delta": 0.0,
      "interrupted_task_resume_rate_delta": 0.0,
      "post_95_extra_distance_delta_abs": 0.0,
      "post_95_search_distance_delta_abs": 0.0,
      "supplemental_task_count_delta_abs": 0.0,
      "task_route_not_found_delta_abs": 0.0,
      "command_rejected_count_delta_abs": 0.0
    },
    "clustered_launch_3uav_dynamic_obstacle": {
      "final_coverage_delta": 0.0,
      "time_to_95_delta_pct": 0.0,
      "total_distance_delta_pct": 0.0,
      "redundant_coverage_delta_pct": 0.0,
      "post_95_extra_distance_delta_pct": 0.0,
      "post_95_search_distance_delta_pct": 0.0,
      "workload_balance_delta": 0.0,
      "workload_balance_active_delta": 0.0,
      "segment_count_delta": 0.0,
      "unique_segment_count_delta": 0.0,
      "segment_workload_balance_delta": 0.0,
      "turn_rate_delta": 0.0,
      "no_fly_violations_delta": 0.0,
      "confirm_success_rate_delta": 0.0,
      "interrupted_task_resume_rate_delta": 0.0,
      "post_95_extra_distance_delta_abs": 0.0,
      "post_95_search_distance_delta_abs": 0.0,
      "supplemental_task_count_delta_abs": 0.0,
      "task_route_not_found_delta_abs": 0.0,
      "command_rejected_count_delta_abs": 0.0
    }
  }
}